linuxacademy_dl/__init__.py
linuxacademy_dl/__main__.py
linuxacademy_dl/_session.py
linuxacademy_dl/assets.py
linuxacademy_dl/cli.py
linuxacademy_dl/course.py
linuxacademy_dl/downloader.py
linuxacademy_dl/exceptions.py
linuxacademy_dl/hls_decrypt.py
linuxacademy_dl/linux_academy.py
linuxacademy_dl/parsers.py
linuxacademy_dl/url_templates.py
linuxacademy_dl/utils.py
linuxacademy_dl-1.0a4.dist-info/DESCRIPTION.rst
linuxacademy_dl-1.0a4.dist-info/METADATA
linuxacademy_dl-1.0a4.dist-info/RECORD
linuxacademy_dl-1.0a4.dist-info/WHEEL
linuxacademy_dl-1.0a4.dist-info/entry_points.txt
linuxacademy_dl-1.0a4.dist-info/metadata.json
linuxacademy_dl-1.0a4.dist-info/top_level.txt
