Metadata-Version: 2.0
Name: linuxacademy-dl
Version: 1.0a4
Summary: Download videos from Linux Academy (linuxacademy.com) for personal offline use
Home-page: https://github.com/vassim/linuxacademy-dl
Author: Vassim Shahir
Author-email: geek@vassim.in
License: BSD 3-Clause License
Platform: UNKNOWN
Classifier: Development Status :: 3 - Alpha
Classifier: Environment :: Console
Classifier: Intended Audience :: Developers
Classifier: License :: OSI Approved :: BSD License
Classifier: Operating System :: OS Independent
Classifier: Programming Language :: Python
Classifier: Programming Language :: Python :: 2
Classifier: Programming Language :: Python :: 2.7
Classifier: Programming Language :: Python :: 3
Classifier: Programming Language :: Python :: 3.5
Classifier: Topic :: Terminals
Classifier: Topic :: Utilities
Classifier: Topic :: Multimedia :: Video
Requires-Dist: pycrypto (>=2.6.1)
Requires-Dist: requests (>=2.12.1)
Requires-Dist: requests-futures (>=0.9.7)
Requires-Dist: six (>=1.10.0)
